scib/__init__.py
scib/_package_tools.py
scib/exceptions.py
scib/integration.py
scib/preprocessing.py
scib/trajectory_inference.py
scib/utils.py
scib/knn_graph/README.md
scib/knn_graph/knn_graph.cpp
scib/knn_graph/knn_graph.o
scib/knn_graph/makefile
scib/metrics/__init__.py
scib/metrics/ari.py
scib/metrics/cell_cycle.py
scib/metrics/clustering.py
scib/metrics/graph_connectivity.py
scib/metrics/highly_variable_genes.py
scib/metrics/isolated_labels.py
scib/metrics/kbet.py
scib/metrics/lisi.py
scib/metrics/metrics.py
scib/metrics/nmi.py
scib/metrics/pcr.py
scib/metrics/silhouette.py
scib/metrics/trajectory.py
scib/metrics/utils.py
scib/resources/cell_cycle_genes_caenorhabditis_elegans.tsv
scib/resources/cell_cycle_genes_danio_rerio.tsv
scib/resources/cell_cycle_genes_homo_sapiens.tsv
scib/resources/cell_cycle_genes_mus_musculus.tsv
scib/resources/convert_genes.py
scib/resources/g2m_genes_tirosh.txt
scib/resources/g2m_genes_tirosh_hm.txt
scib/resources/s_genes_tirosh.txt
scib/resources/s_genes_tirosh_hm.txt
scib-1.1.7.dist-info/LICENSE.txt
scib-1.1.7.dist-info/METADATA
scib-1.1.7.dist-info/WHEEL
scib-1.1.7.dist-info/top_level.txt
scib-1.1.7.dist-info/RECORD
