Metadata-Version: 2.2
Name: scib
Version: 1.1.7
Summary: Evaluating single-cell data integration methods
Home-page: https://github.com/theislab/scib
Author: Malte D. Luecken, Maren Buettner, Daniel C. Strobl, Michaela F. Mueller
Author-email: malte.luecken@helmholtz-muenchen.de, michaela.mueller@helmholtz-muenchen.de
License: MIT
Project-URL: Pipeline, https://github.com/theislab/scib-pipeline
Project-URL: Reproducibility, https://theislab.github.io/scib-reproducibility
Project-URL: Bug Tracker, https://github.com/theislab/scib/issues
Keywords: benchmarking,single cell,data integration
Classifier: Development Status :: 3 - Alpha
Classifier: Intended Audience :: Developers
Classifier: Intended Audience :: Science/Research
Classifier: Topic :: Software Development :: Build Tools
Classifier: License :: OSI Approved :: MIT License
Classifier: Programming Language :: Python :: 3
Classifier: Programming Language :: Python :: 3.9
Classifier: Programming Language :: Python :: 3.10
Classifier: Programming Language :: Python :: 3.11
Requires-Python: >=3.9
License-File: LICENSE.txt
Requires-Dist: numpy
Requires-Dist: pandas>=2
Requires-Dist: seaborn
Requires-Dist: matplotlib
Requires-Dist: numba
Requires-Dist: scanpy>=1.5
Requires-Dist: anndata>=0.7.2
Requires-Dist: h5py
Requires-Dist: scipy
Requires-Dist: scikit-learn
Requires-Dist: scikit-misc
Requires-Dist: leidenalg
Requires-Dist: umap-learn
Requires-Dist: pydot
Requires-Dist: igraph>=0.10
Requires-Dist: llvmlite
Requires-Dist: deprecated
Provides-Extra: rpy2
Requires-Dist: rpy2>=3; extra == "rpy2"
Requires-Dist: anndata2ri; extra == "rpy2"
Provides-Extra: test
Requires-Dist: pytest; extra == "test"
Requires-Dist: pytest-icdiff; extra == "test"
Requires-Dist: pytest-cov; extra == "test"
Requires-Dist: codecov; extra == "test"
Provides-Extra: dev
Requires-Dist: build; extra == "dev"
Requires-Dist: twine; extra == "dev"
Requires-Dist: isort; extra == "dev"
Requires-Dist: bump2version; extra == "dev"
Requires-Dist: pre-commit; extra == "dev"
Provides-Extra: docs
Requires-Dist: sphinx; extra == "docs"
Requires-Dist: sphinx_rtd_theme; extra == "docs"
Requires-Dist: myst_parser; extra == "docs"
Requires-Dist: sphinx-automodapi; extra == "docs"
Provides-Extra: louvain
Requires-Dist: igraph; extra == "louvain"
Requires-Dist: louvain>=0.8; extra == "louvain"
Provides-Extra: bbknn
Requires-Dist: bbknn==1.3.9; extra == "bbknn"
Provides-Extra: scanorama
Requires-Dist: scanorama>=1.7.4; extra == "scanorama"
Provides-Extra: mnn
Requires-Dist: mnnpy==0.1.9.5; extra == "mnn"
Provides-Extra: scgen
Requires-Dist: scgen>=2.1.0; extra == "scgen"
Provides-Extra: scvi
Requires-Dist: scvi-tools>=0.16; extra == "scvi"
Provides-Extra: trvae
Requires-Dist: trvae==1.1.2; extra == "trvae"
Provides-Extra: trvaep
Requires-Dist: trvaep==0.1.0; extra == "trvaep"
Provides-Extra: desc
Requires-Dist: desc==2.0.3; extra == "desc"
Provides-Extra: harmony
Requires-Dist: harmony-pytorch; extra == "harmony"
